LICENCE
scrapyscript/__init__.py
scrapyscript/scrapy.cfg
scrapyscript-1.1.4.dist-info/WHEEL
scrapyscript-1.1.4.dist-info/METADATA
scrapyscript-1.1.4.dist-info/RECORD
