Metadata-Version: 2.1
Name: scrapyscript
Version: 1.1.4
Summary: Run a Scrapy spider programmatically from a script or a Celery task - no project required.
Home-page: https://github.com/jschnurr/scrapyscript
License: MIT
Keywords: scrapy
Author: Jeff Schnurr
Author-email: jschnurr@gmail.com
Requires-Python: >=3.8,<4.0
Classifier: Framework :: Scrapy
Classifier: Intended Audience :: Developers
Classifier: License :: OSI Approved :: MIT License
Classifier: Programming Language :: Python :: 3
Classifier: Programming Language :: Python :: 3.10
Classifier: Programming Language :: Python :: 3.8
Classifier: Programming Language :: Python :: 3.9
Requires-Dist: Scrapy (>=2.5.1,<3.0.0)
Requires-Dist: billiard (>=3.6,<4.0)
Project-URL: Repository, https://github.com/jschnurr/scrapyscript
